{
  "name": "Baptist",
  "parent": 9,
  "Denomination": [
    { "name": "Southern Baptist Convention" },
    { "name": "National Baptist Convention, USA, Inc." },
    { "name": "Nigerian Baptist Convention" },
    { "name": "National Missionary Baptist Convention of America" },
    { "name": "National Baptist Convention of America, Inc." },
    { "name": "Baptist Union of Uganda" },
    { "name": "Baptist Community of Congo" },
    { "name": "Baptist Convention of Tanzania" },
    { "name": "Baptist General Convention of Texas" },
    { "name": "Brazilian Baptist Convention" },
    { "name": "Progressive National Baptist Convention" },
    { "name": "Council of Baptist Churches in Northeast India" },
    { "name": "American Baptist Churches USA" },
    { "name": "Baptist Bible Fellowship International" },
    { "name": "Lott Carey Foreign Mission Convention" },
    { "name": "Baptist Community of the Congo River" },
    { "name": "National Primitive Baptist Convention of the U.S.A." },
    { "name": "Myanmar Baptist Convention" },
    { "name": "Cooperative Baptist Fellowship" },
    { "name": "Baptist General Association of Virginia" },
    { "name": "Baptist Convention of Kenya" },
    { "name": "Nagaland Baptist Church Council" },
    { "name": "Korea Baptist Convention" },
    { "name": "Samavesam of Telugu Baptist Churches" },
    { "name": "Orissa Evangelical Baptist Crusade" },
    { "name": "National Baptist Convention (Brazil)" },
    { "name": "Baptist Convention of Malawi" },
    { "name": "Garo Baptist Convention" },
    { "name": "Convention of Philippine Baptist Churches" },
    { "name": "Ghana Baptist Convention" },
    { "name": "Union of Baptist Churches in Rwanda" },
    { "name": "Conservative Baptist Association of America" },
    { "name": "National Association of Free Will Baptists" },
    { "name": "Convention of Visayas and Mindanao of Southern Baptist Churches" },
    { "name": "Manipur Baptist Convention" },
    { "name": "Evangelical Baptist Church of the Central African Republic" },
    { "name": "Converge" },
    { "name": "Seventh Day Baptists" }
  ]
}
